{
  "schema_version": 7,
  "item_id": "hndaily-19684649",
  "published_date": "2026-07-08",
  "collected_date": "2026-07-10",
  "page_number": "001",
  "page_name": "头版",
  "page_sequence": 9,
  "author": "",
  "enrichment_status": "legacy-derived",
  "scope": "mixed",
  "scope_evidence": "全国首单保税LNG罐箱国际转运业务落地洋浦",
  "subjects": [],
  "locations": [],
  "topics": [],
  "event_relation": {
    "relation": "none",
    "event_id": null,
    "event_name": null,
    "evidence": null,
    "update_summary": null
  },
  "block": {
    "source": "海南日报",
    "title": "全国首单保税LNG罐箱国际转运业务落地洋浦",
    "content": "7月7日，20个保税LNG（液化天然气）罐箱在洋浦国际集装箱码头装船启航，驶向越南，标志着全国首单保税LNG罐箱国际转运业务在洋浦落地。据了解，装载保税LNG罐箱的香港籍船舶“永盛99”轮自越南抵达广东装货后来到洋浦转运，最终驶往越南。\n\n文/海南日报全媒体记者 吴心怡 图/洋浦海事局",
    "ai_summary": "7月7日，20个保税LNG（液化天然气）罐箱在洋浦国际集装箱码头装船启航，驶向越南，标志着全国首单保税LNG罐箱国际转运业务在洋浦落地。",
    "original_url": "http://news.hndaily.cn/html/2026-07/08/content_58464_19684649.htm"
  }
}
