{
  "schema_version": 7,
  "item_id": "hndaily-20260713-58468-19697315",
  "published_date": "2026-07-13",
  "collected_date": "2026-07-19",
  "page_number": "005",
  "page_name": "中国新闻",
  "page_sequence": 2,
  "author": "",
  "enrichment_status": "complete",
  "scope": "national",
  "scope_evidence": "上半年高频数据\n折射我国经济稳中向优",
  "subjects": [],
  "locations": [],
  "topics": [
    {
      "topic_id": "economy-data",
      "name": "经济数据",
      "evidence": "上半年高频数据\n折射我国经济稳中向优"
    }
  ],
  "event_relation": {
    "relation": "none",
    "event_id": null,
    "event_name": null,
    "evidence": null,
    "update_summary": null
  },
  "block": {
    "source": "海南日报",
    "title": "上半年高频数据\n折射我国经济稳中向优",
    "content": "新华社北京7月12日电 （记者潘洁）记者12日从国家发展改革委国家信息中心了解到，今年上半年，线下商圈人流热度同比增长5.7%，消费延续向好态势；战略性新兴产业相关专利授权量同比增长15.6%，人工智能、人形机器人等前沿领域的资本投资金额同比增长118.4%，经济高质量发展的创新引擎动力不断增强。\n\n线下消费大数据显示，1至6月份，线下消费支付金额同比增长2.7%，其中商品消费、服务消费同比分别增长4.0%、0.8%。电子商品需求较高，同比增长9.5%；文旅相关的交通、餐饮相关消费热度持续高涨，同比分别增长6.1%、4.9%；线下商圈人流热度同比增长5.7%。\n\n“上半年，扩内需、促消费政策组合拳精准发力，供需两端协同改善，文旅消费、智能消费等领域增势良好，总体呈现商品提质、服务扩容、场景升温的特征，带动消费大盘延续回稳向好态势。”国家发展改革委国家信息中心大数据发展部副研究员邢玉冠说。\n\n今年以来，高技术领域投资热度持续攀升。1至6月份，人工智能、人形机器人等前沿领域的资本投资金额同比增长118.4%，算力等领域的数字基础设施项目中标金额同比增长23.0%。\n\n工业方面，今年上半年，工业运行发展走势稳、产业动能新、结构质量优。1至6月份，工业园区生产热度指数同比上升3.9%，初创企业经营活力同比上升1.0%，技术创新型企业经营活力同比上升3.1%。战略性新兴产业相关专利授权量同比增长15.6%，其中6月同比增长30.3%。与人工智能相关的专利授权量上半年同比增长34.8%。\n\n邢玉冠表示，上半年，在更加积极有为的宏观政策支撑下，我国经济保持稳中有进、稳中向优、稳中蓄能的良好态势，经济韧性持续增强，发展动能加快转换，为“十五五”开好局、起好步奠定了坚实基础。",
    "ai_summary": "今年上半年全国线下商圈人流热度同比增长5.7%，人工智能、人形机器人等前沿领域资本投资增长118.4%。",
    "original_url": "http://news.hndaily.cn/html/2026-07/13/content_58468_19697315.htm"
  }
}
