{
  "schema_version": 7,
  "item_id": "hndaily-20260714-58467-19700650",
  "published_date": "2026-07-14",
  "collected_date": "2026-07-19",
  "page_number": "004",
  "page_name": "本省新闻",
  "page_sequence": 2,
  "author": "",
  "enrichment_status": "complete",
  "scope": "hainan",
  "scope_evidence": "暑假校外培训机构怎么选？",
  "subjects": [],
  "locations": [],
  "topics": [
    {
      "topic_id": "education-talent",
      "name": "教育人才",
      "evidence": "暑假校外培训机构怎么选？"
    }
  ],
  "event_relation": {
    "relation": "none",
    "event_id": null,
    "event_name": null,
    "evidence": null,
    "update_summary": null
  },
  "block": {
    "source": "海南日报",
    "title": "暑假校外培训机构怎么选？",
    "content": "本报海口7月13日讯（海南日报全媒体记者张琬茜 通讯员林劼）当前，海南中小学校已开启“暑假模式”。7月13日，省教育厅向全省中小学校家长发布相关提示，提倡科学合理安排学生假期生活，加强亲子陪伴，理性看待校外培训，保障孩子度过轻松愉悦的假期。如确有参加校外学习的需求，建议选择体育、科技、文化艺术等非学科类项目，培养学生兴趣特长，挖掘个人潜能，全面提升综合素养。\n\n那么，家长在选择校外培训机构时，应注意核查哪些方面？省教育厅相关负责人表示，机构资质有“三查”，即查证照、查师资、查平台。\n\n具体来看，一是查证照，核查机构是否持有《民办学校办学许可证》和《营业执照》（或《民办非企业单位登记证书》），核对实际办学地址、培训场所、培训内容，与证照登记信息保持一致；二是查师资，查看机构公示栏，确认授课教师已公示经审核合格的教师资格证明材料；三是查平台，通过全国校外教育培训监管与服务综合平台或教育部推出的“校外培训家长端”APP办理选课购课业务。\n\n针对校外培训缴费，省教育厅提醒广大家长，一次性缴费不得超过3个月，课时不得超过60学时，且收费总额不得高于5000元；如遇机构超额预收费用，应坚决予以拒绝，并及时向属地监管部门举报；切勿以现金形式缴费，切勿通过微信、支付宝、银行卡转账，将资金转入校外培训资金监管专用账户以外的账户，切实防范资金安全风险。家长可通过官方“校外培训家长端”APP完成缴费，系统将自动生成《中小学生校外培训服务合同（示范文本）》，有效保障选课、缴费、消课、退费等各项合法权益。\n\n校外培训安全问题同样至关重要。学生和家长应实地排查培训机构场地安全隐患，确认消防通道畅通、消防设施配备齐全，办学环境干净整洁。家长应常态化对孩子开展交通安全、防溺水、防欺凌、防踩踏、以及用火电气安全等教育，持续提升未成年人自我防护意识与避险能力。\n\n此外，为确保孩子人身安全，建议尽量由监护人亲自接送孩子往返培训地点，避免未成年人独自外出，保障学生人身安全。若无法在培训期间全程陪护孩子，必须与培训机构签订安全监护责任书，明确双方监护职责。",
    "ai_summary": "海南提醒家长选择校外培训时核查证照、师资和监管平台，单次缴费不得超过3个月、60课时或5000元。",
    "original_url": "http://news.hndaily.cn/html/2026-07/14/content_58467_19700650.htm"
  }
}
