{
  "schema_version": 7,
  "item_id": "hndaily-20260714-58471-19700718",
  "published_date": "2026-07-14",
  "collected_date": "2026-07-19",
  "page_number": "008",
  "page_name": "教育周刊",
  "page_sequence": 1,
  "author": "",
  "enrichment_status": "complete",
  "scope": "mixed",
  "scope_evidence": "国际教育创新岛尽显“磁吸力”",
  "subjects": [],
  "locations": [
    {
      "location_id": "hainan-haikou",
      "name": "海口市",
      "code": "460100",
      "level": "prefecture",
      "evidence": "海口市"
    },
    {
      "location_id": "hainan",
      "name": "海南省",
      "code": "460000",
      "level": "province",
      "evidence": "海南省"
    }
  ],
  "topics": [
    {
      "topic_id": "education-talent",
      "name": "教育人才",
      "evidence": "国际教育创新岛尽显“磁吸力”"
    }
  ],
  "event_relation": {
    "relation": "none",
    "event_id": null,
    "event_name": null,
    "evidence": null,
    "update_summary": null
  },
  "block": {
    "source": "海南日报",
    "title": "国际教育创新岛尽显“磁吸力”",
    "content": "■ 海南日报全媒体记者 张琬茜 通讯员 王柳芸\n\n国务院日前印发《教育发展“十五五”规划》，对“十五五”时期加快建设教育强国作出部署。其中，提出深入推进海南国际教育创新岛建设。\n\n近年来，在“中央统筹、部委支持、省抓落实”的统筹推动下，海南以国际教育创新岛建设为抓手，以办好人民满意和自贸港需要的教育为目标，致力服务国家重大战略和区域经济社会发展需求，统筹推进教育、科技、人才“三位一体”发展。\n\n截至目前，全省累计签约引进55所高校，累计获批41个本科层次及以上中外合作办学机构（项目）。不出国门，到儋州洋浦就能体验德国“实践嵌入式”教育；广招新生，海南洛桑旅游大学今年计划面向全国招生500人；深化合作，今年全省新增获批9个中外合作办学机构（项目）、新增25所国际学生培养单位……海南高水平教育对外开放吸引力持续加码，国际教育创新岛上一片生机盎然。\n\n下好资源汇聚“先手棋”\n\n◆持续汇聚一流教育资源，探索“大共享＋小学院”“五互一共”人才培养新模式。截至目前，我省累计签约引进55所高校；累计获批本科层次及以上中外合作办学机构（项目）41个，涉及中方高校17所，外方高校33所。其中，中方合作高校中，“双一流”高校占比64.7％；外方合作高校中，世界排名前300的高校占比42.4％。\n\n◆2026年上半年，新增获批的9个中外合作办学机构（项目）整体呈现出办学资源更加优质、填补学科短板和空白、契合产业发展所需等特点。\n\n◆2026年上半年，全省新增25所国际学生培养单位。全省招收和培养国际学生单位达90所，覆盖外籍人员相对聚集的海口、三亚、澄迈、万宁、琼海等10个市县，为外籍人员子女在琼接受教育提供更多选择。\n\n◆海南大学全力推进热区高校联盟建设，2026年上半年新增加纳通信技术大学、马来西亚博特拉大学、印尼茂物农业大学等高校，联盟成员现已覆盖50个国家和地区的121所高校与科研机构。\n\n◆截至目前，海南陵水黎安国际教育创新试验区签约引进30所国内外知名高校，累计获批24个本科层次及以上中外合作办学机构（项目），师生规模超万人。\n\n◆截至目前，三亚崖州湾科技城高新区累计引进19所院校，布局作物遗传育种、农艺与种业、海洋科学、船舶与海洋工程等160余个学科专业，招收海南专项博士、硕士研究生规模达8300余名。\n\n◆7月5日，由司法部、海南省人民政府、中国政法大学共同支持建设的中国政法大学中国—东盟学院正式揭牌。学院拟落户海南陵水黎安国际教育创新试验区，重点培养东盟国家高端涉外法治人才，为中国—东盟命运共同体建设、海南自由贸易港高水平开放提供重要支撑。\n\n做好产教适配“大文章”\n\n◆作为中国境内首个境外高校独立办学高校，海南比勒费尔德应用科学大学2026年计划面向全国招收800名新生，计算机科学与技术、电子信息科学与技术、物流工程、工商管理等7个专业直接服务于海南自贸港在高端制造、数字经济和现代物流领域的关键产业。\n\n◆海南洛桑旅游大学2026年计划面向全国19个省（区、市）投放500个招生计划，开设酒店管理、烹饪与营养教育两个核心专业，采用理论与实践深度融合的培养模式，毕业生可同时获得中外双方学士学位。\n\n◆新增获批西安交通大学与加拿大不列颠哥伦比亚大学合作举办的碳中和科学与工程专业本科教育项目，紧扣国家“双碳”战略与绿色发展趋势，与“向绿图强”战略布局高度契合，填补了全省绿色低碳类新兴工科专业空白。\n\n◆新增获批中国地质大学（北京）与英国伯明翰城市大学合作举办的宝石及材料工艺学专业、产品设计专业2个本科教育项目，精准对接海南国际旅游消费中心建设和高端文旅产品设计需求，助力自贸港文旅产业提质升级。\n\n◆新增获批中国地质大学（北京）与英国阿伯丁大学合作举办资源勘查工程专业本科教育项目，为海南深海油气、矿产等领域产业发展培养兼具地质勘查专业能力与国际视野的高层次专业人才，为“再造一个海上海南”的战略目标落地提供坚实人才支撑与智力支持。\n\n织好开放育人“连心网”\n\n◆持续做好国际学生招生培养，2025年国际学生规模同比增长43.8％，出国留学规模增长7.99％。\n\n◆2025—2026学年，海南省政府奖学金生数量同比增长16.9％。\n\n◆在海口市开启试点专项授权，以财政生均教育事业费支出为基底，叠加双语服务等增量成本，统筹住宿运维支出，确定公办学校招收国际学生小学学费6900元／生·学期、初中学费8900元／生·学期、住宿费800元／生·学期，为外籍人员子女入读公办学校开启新通道。\n\n◆截至2026年6月，海南陵水黎安国际教育创新试验区统筹开放337门共享课程，累计达509学分、7737学时，选课学生超7000人次，实现共享课程对入驻高校100％全覆盖、共享课程数量持续增长。\n\n◆海南医科大学西英格兰学院打造国际化医学人才高地，首届硕士毕业生留琼就业率为61.7％，国际护理实践专业首届毕业生毕业率、就业率均达到100％。\n\n◆海南师范大学以多层次中外合作办学夯实国际化育人根基，现有3个教育部获批中外合作本科机构（项目）。中俄广播电视编导项目学生斩获圣彼得堡国际大学生电影节最佳编剧奖；中意环境设计项目学生获国家级奖项27人次，携黎锦非遗亮相米兰设计周并斩获双项大奖。\n\n◆北京邮电大学玛丽女王海南学院办学四年来学生累计获省部级及以上奖项234项、474人次，2022级首届本科生整体深造率达81.5％，其中，出国留学学生中87.5％进入QS世界排名前100高校深造。\n\n◆电子科技大学格拉斯哥海南学院依托中英优质教育资源办学，四年来学科竞赛屡创佳绩，累计揽获百余项国家级、省级奖项。首届毕业生总体深造率达91.09％，其中，国（境）外深造率66.34％，QS世界排名前20高校录取占比64.18％、前100录取占比达95.52％。",
    "ai_summary": "海南已签约引进55所高校、获批41个本科以上中外合作办学机构或项目，国际教育开放继续扩大。",
    "original_url": "http://news.hndaily.cn/html/2026-07/14/content_58471_19700718.htm"
  }
}
