{
  "schema_version": 7,
  "item_id": "hndaily-20260716-58465-19707959",
  "published_date": "2026-07-16",
  "collected_date": "2026-07-19",
  "page_number": "002",
  "page_name": "要闻",
  "page_sequence": 5,
  "author": "",
  "enrichment_status": "complete",
  "scope": "national",
  "scope_evidence": "上半年我国GDP同比增长4.7%",
  "subjects": [],
  "locations": [],
  "topics": [
    {
      "topic_id": "economy-data",
      "name": "经济数据",
      "evidence": "GDP"
    }
  ],
  "event_relation": {
    "relation": "none",
    "event_id": null,
    "event_name": null,
    "evidence": null,
    "update_summary": null
  },
  "block": {
    "source": "海南日报",
    "title": "上半年我国GDP同比增长4.7%",
    "content": "据新华社北京7月15日电 （记者何晓 王雨萧）国家统计局15日发布数据显示，初步核算，上半年我国国内生产总值（GDP）695704亿元，按不变价格计算，同比增长4.7%。\n\n夏粮增产丰收，工业生产较快增长，服务业平稳增长。全国夏粮总产量15075万吨，比上年增加100万吨，增长0.7%。上半年，全国规模以上工业增加值同比增长5.4%；服务业增加值同比增长5.2%。\n\n消费市场继续扩容，固定资产投资下降，货物进出口快速增长。上半年，社会消费商品和服务零售总额同比增长2.7%，其中服务零售额增长5.3%，商品零售额增长1.1%；全国固定资产投资（不含农户）226370亿元，同比下降5.7%；货物进出口总额254686亿元，同比增长16.9%。\n\n居民消费价格温和上涨，就业形势总体稳定，居民收入平稳增长。上半年，全国居民消费价格指数（CPI）同比上涨1.0%；全国城镇调查失业率平均值为5.2%；全国居民人均可支配收入22981元，同比名义增长5.2%，扣除价格因素实际增长4.2%。\n\n“总的来看，上半年国民经济运行在合理区间，新质生产力培育壮大，高质量发展向新向优。也要看到，外部不稳定不确定因素较多，国内供强需弱矛盾突出，经济向好基础还需巩固。”国家统计局副局长毛盛勇在15日举行的国新办新闻发布会上说。",
    "ai_summary": "据新华社北京7月15日电 （记者何晓 王雨萧）国家统计局15日发布数据显示，初步核算，上半年我国国内生产总值（GDP）695704亿元，按不变价格计算，同比增长4.7%。",
    "original_url": "http://news.hndaily.cn/html/2026-07/16/content_58465_19707959.htm"
  }
}
